CHANGES.rst
LICENSE
MANIFEST.in
NOTICE
OVERVIEW.rst
README.rst
badges.rst
setup.py
doc/Makefile
doc/__init__.py
doc/api.rst
doc/browser.rst
doc/changes.rst
doc/conf.py
doc/configuration.rst
doc/deployment.rst
doc/develop_plugins.rst
doc/dhcp.rst
doc/dns.rst
doc/donpedro.rst
doc/faq.rst
doc/index.rst
doc/installation.rst
doc/license.rst
doc/make.bat
doc/notifications.rst
doc/overview.rst
doc/permissions.rst
doc/quickstart.rst
doc/ralph-logo.png
doc/scan.rst
doc/_static/add-data-center-asset-form.png
doc/_static/add_licence.png
doc/_static/add_support.png
doc/_static/asset_add_part.png
doc/_static/bulk-1.png
doc/_static/bulk-2.png
doc/_static/custom_modules-module.png
doc/_static/edit-device-status.png
doc/_static/ralph_quick_start_add_asset.png
doc/_static/ralph_quick_start_add_asset_form.png
doc/_static/ralph_quick_start_quick_scan.png
doc/_static/ralph_quick_start_scan.png
doc/_static/ralph_quick_start_scan_result.png
doc/_static/scan_choose_ip_for_scan.png
doc/_static/scan_choose_plugins.png
doc/_static/scan_net_auto.png
doc/_static/scan_summary.png
doc/_static/scrooge_costs_report.png
doc/_static/scrooge_costs_report2.png
doc/_static/scrooge_monthly_accept.png
doc/_static/scrooge_monthly_costs1.png
doc/_static/scrooge_monthly_costs2.png
doc/_static/scrooge_start.png
doc/optional_modules/index.rst
doc/optional_modules/cmdb/api.rst
doc/optional_modules/cmdb/index.rst
doc/optional_modules/cmdb/overview.rst
doc/theme/ADCtheme/README.rst
doc/theme/ADCtheme/layout.html
doc/theme/ADCtheme/theme.conf
doc/theme/ADCtheme/static/adctheme.css
doc/theme/ADCtheme/static/breadcrumb_background.png
doc/theme/ADCtheme/static/documentation.png
doc/theme/ADCtheme/static/header_sm_mid.png
doc/theme/ADCtheme/static/scrn1.png
doc/theme/ADCtheme/static/scrn2.png
doc/theme/ADCtheme/static/searchfield_leftcap.png
doc/theme/ADCtheme/static/searchfield_repeat.png
doc/theme/ADCtheme/static/searchfield_rightcap.png
doc/theme/ADCtheme/static/title_background.png
src/ralph.egg-info/PKG-INFO
src/ralph.egg-info/SOURCES.txt
src/ralph.egg-info/dependency_links.txt
src/ralph.egg-info/entry_points.txt
src/ralph.egg-info/not-zip-safe
src/ralph.egg-info/pbr.json
src/ralph.egg-info/requires.txt
src/ralph.egg-info/top_level.txt
