Metadata-Version: 1.1
Name: ralph
Version: 2.3.1
Summary: Ralph is a full-featured Asset Management, DCIM and CMDB system for data center and backoffice areas.
Home-page: http://ralph.allegrogroup.com/
Author: Grupa Allegro Sp. z o.o. and Contributors
Author-email: pylabs@allegro.pl
License: Apache Software License v2.0
Platform: any
Classifier: Development Status :: 5 - Production/Stable
Classifier: Framework :: Django
Classifier: Intended Audience :: System Administrators
Classifier: License :: OSI Approved :: Apache Software License
Classifier: Natural Language :: English
Classifier: Operating System :: POSIX
Classifier: Operating System :: MacOS :: MacOS X
Classifier: Operating System :: Microsoft :: Windows :: Windows NT/2000
Classifier: Programming Language :: Python
Classifier: Programming Language :: Python :: 2.7
Classifier: Programming Language :: Python :: 2 :: Only
Classifier: Topic :: Internet :: WWW/HTTP
